ews_cli
